{"type": "Feature", "id": 12523770, "properties": {"woe:id": 12523770, "woe:parent_id": 368444, "woe:name": "Zapatoca Airport", "woe:placetype": 14, "woe:placetype_name": "Airport", "woe:lang": "ENG", "iso:country": "CO", "meta:provider": ["geoplanet:7.3.1", "geoplanet:7.3.2", "geoplanet:7.4.0", "geoplanet:7.4.1", "geoplanet:7.5.1", "geoplanet:7.5.2", "geoplanet:7.6.0", "geoplanet:7.8.1", "geoplanet:7.9.0", "geoplanet:7.10.0", "geoplanet:8.0.0", "woeplanet:8.0.0"], "meta:indexed": "2020-08-20T20:26:14.627542", "woe:alias_ENG_V": ["AZT Airport", "AZT"], "meta:updated": "2020-08-22T02:50:32.768598", "woe:hierarchy": {"continent": 24865673, "country": 23424787, "town": 0, "planet": 1, "county": 26797492, "suburb": 0, "state": 2345071, "region": 0, "localadmin": 0}, "woe:timezone_id": 28350741, "woe:hash": "d35yu2utzr3k", "woe:centroid": [-73.283302, 6.81667], "geom:latitude": 6.81667, "geom:longitude": -73.283302, "geom:hash": "d35yu2utzr3k", "woe:latitude": 6.81667, "geom:centroid": [-73.283302, 6.81667], "woe:longitude": -73.283302, "woe:repo": "woeplanet-airport-co"}, "geometry": {"coordinates": [-73.283302, 6.81667], "type": "Point"}}