{"type": "Feature", "id": 12512398, "properties": {"woe:id": 12512398, "woe:parent_id": 369150, "woe:name": "Montelibano Airport", "woe:placetype": 14, "woe:placetype_name": "Airport", "woe:lang": "ENG", "iso:country": "CO", "meta:provider": ["geoplanet:7.3.1", "geoplanet:7.3.2", "geoplanet:7.4.0", "geoplanet:7.4.1", "geoplanet:7.5.1", "geoplanet:7.5.2", "geoplanet:7.6.0", "geoplanet:7.8.1", "geoplanet:7.9.0", "geoplanet:7.10.0", "geoplanet:8.0.0", "woeplanet:8.0.0"], "meta:indexed": "2020-08-20T20:26:14.566987", "woe:alias_ENG_V": ["MTB Airport", "MTB"], "meta:updated": "2020-08-22T02:50:32.735326", "woe:hierarchy": {"continent": 24865673, "country": 23424787, "town": 0, "planet": 1, "county": 26797032, "suburb": 0, "state": 2345058, "region": 0, "localadmin": 0}, "woe:timezone_id": 28350741, "woe:hash": "d36m7ux61ywy", "woe:centroid": [-75.411102, 7.9792], "geom:latitude": 7.9792, "geom:longitude": -75.411102, "geom:hash": "d36m7ux61ywy", "woe:latitude": 7.9792, "geom:centroid": [-75.411102, 7.9792], "woe:longitude": -75.411102, "woe:repo": "woeplanet-airport-co"}, "geometry": {"coordinates": [-75.411102, 7.9792], "type": "Point"}}