{"type": "Feature", "id": 12512413, "geometry": {"type": "Point", "coordinates": [-75.6828, 5.0897]}, "properties": {"woe:id": 12512413, "woe:parent_id": 350903, "woe:name": "Santagueda Airport", "woe:placetype": 14, "woe:placetype_name": "Airport", "woe:lang": "ENG", "iso:country": "CO", "meta:provider": ["geoplanet:7.3.1", "geoplanet:7.3.2", "geoplanet:7.4.0", "geoplanet:7.4.1", "geoplanet:7.5.1", "geoplanet:7.5.2", "geoplanet:7.6.0", "geoplanet:7.8.1", "geoplanet:7.9.0", "geoplanet:7.10.0", "geoplanet:8.0.0", "woeplanet:8.0.0"], "meta:indexed": "2020-08-20T20:26:14.580415", "meta:updated": "2020-10-14T12:07:51.104467", "woe:hierarchy": {"continent": 24865673, "country": 23424787, "town": 0, "planet": 1, "county": 26796935, "suburb": 0, "state": 2345053, "region": 0, "localadmin": 0}, "woe:timezone_id": 28350741, "woe:hash": "d2fhvy93wuy5", "woe:centroid": [-75.6828, 5.0897], "geom:latitude": 5.0897, "geom:longitude": -75.6828, "geom:hash": "d2fhvy93wuy5", "woe:latitude": 5.0897, "geom:centroid": [-75.6828, 5.0897], "woe:longitude": -75.6828, "woe:repo": "woeplanet-airport-co", "geom:area": 0.0, "woe:scale": 19}}