{"type": "Feature", "id": 12524508, "geometry": {"type": "Point", "coordinates": [-74.580116, 6.00232]}, "properties": {"woe:id": 12524508, "woe:parent_id": 368366, "woe:name": "Puerto Boyaca Airport", "woe:placetype": 14, "woe:placetype_name": "Airport", "woe:lang": "ENG", "iso:country": "CO", "meta:provider": ["geoplanet:7.3.1", "geoplanet:7.3.2", "geoplanet:7.4.0", "geoplanet:7.4.1", "geoplanet:7.5.1", "geoplanet:7.5.2", "geoplanet:7.6.0", "geoplanet:7.8.1", "geoplanet:7.9.0", "geoplanet:7.10.0", "geoplanet:8.0.0", "woeplanet:8.0.0"], "meta:indexed": "2020-08-20T20:26:14.666064", "woe:alias_ENG_V": ["PYA Airport", "PYA", "Pto Boyaca Airport"], "meta:updated": "2020-10-14T12:07:51.161592", "woe:hierarchy": {"continent": 24865673, "country": 23424787, "town": 0, "planet": 1, "county": 26796687, "suburb": 0, "state": 2345048, "region": 0, "localadmin": 0}, "woe:timezone_id": 28350741, "woe:hash": "d34fnusqj3dc", "woe:centroid": [-74.580116, 6.00232], "geom:latitude": 6.00232, "geom:longitude": -74.580116, "geom:hash": "d34fnusqj3dc", "woe:latitude": 6.00232, "geom:centroid": [-74.580116, 6.00232], "woe:longitude": -74.580116, "woe:repo": "woeplanet-airport-co", "geom:area": 0.0, "woe:scale": 19}}