{"type": "Feature", "id": 12524523, "geometry": {"type": "Point", "coordinates": [-74.400002, 3.21667]}, "properties": {"woe:id": 12524523, "woe:parent_id": 369512, "woe:name": "Uribe Airport", "woe:placetype": 14, "woe:placetype_name": "Airport", "woe:lang": "ENG", "iso:country": "CO", "meta:provider": ["geoplanet:7.3.1", "geoplanet:7.3.2", "geoplanet:7.4.0", "geoplanet:7.4.1", "geoplanet:7.5.1", "geoplanet:7.5.2", "geoplanet:7.6.0", "geoplanet:7.8.1", "geoplanet:7.9.0", "geoplanet:7.10.0", "geoplanet:8.0.0", "woeplanet:8.0.0"], "meta:indexed": "2020-08-20T20:26:14.678610", "woe:alias_ENG_V": ["URI Airport", "URI"], "meta:updated": "2020-10-14T12:07:51.168350", "woe:hierarchy": {"continent": 24865673, "country": 23424787, "town": 0, "planet": 1, "county": 26797266, "suburb": 0, "state": 2345064, "region": 0, "localadmin": 0}, "woe:timezone_id": 28350741, "woe:hash": "d2e46cxd6q9x", "woe:centroid": [-74.400002, 3.21667], "geom:latitude": 3.21667, "geom:longitude": -74.400002, "geom:hash": "d2e46cxd6q9x", "woe:latitude": 3.21667, "geom:centroid": [-74.400002, 3.21667], "woe:longitude": -74.400002, "woe:repo": "woeplanet-airport-co", "geom:area": 0.0, "woe:scale": 19}}